CHANGES.txt
MANIFEST.in
README.rst
requirements.txt
setup.py
pgsql2gist/__init__.py
pgsql2gist/cli.py
pgsql2gist/command_line.py
pgsql2gist/constructors.py
pgsql2gist/gisthandler.py
pgsql2gist/pgconn.py
pgsql2gist.egg-info/PKG-INFO
pgsql2gist.egg-info/SOURCES.txt
pgsql2gist.egg-info/dependency_links.txt
pgsql2gist.egg-info/entry_points.txt
pgsql2gist.egg-info/requires.txt
pgsql2gist.egg-info/top_level.txt