Metadata-Version: 1.1
Name: pgsql2gist
Version: 0.3.0
Summary: Create maps using the Github Gist API as GeoJSON or TopoJSON, directly from PostGIS.
Home-page: https://github.com/mattmakesmaps/pgsql2gist
Author: Matthew Kenny
Author-email: matthewkenny AT gmail DOT com
License: GNU LESSER GENERAL PUBLIC LICENSE
Keywords: gis gists postgis postgresql geojson
Platform: UNKNOWN
Classifier: Development Status :: 4 - Beta
Classifier: Topic :: Scientific/Engineering :: GIS
Classifier: License :: OSI Approved :: GNU Lesser General Public License v2 or later (LGPLv2+)
Classifier: Intended Audience :: Developers
